uuidgen/__init__.py
uuidgen/cli.py
uuidgen-1.0.2.dist-info/licenses/LICENSE
uuidgen-1.0.2.dist-info/METADATA
uuidgen-1.0.2.dist-info/WHEEL
uuidgen-1.0.2.dist-info/entry_points.txt
uuidgen-1.0.2.dist-info/top_level.txt
uuidgen-1.0.2.dist-info/RECORD
