Metadata-Version: 2.4
Name: uuidgen
Version: 1.0.2
Summary: a tool to generate UUID from terminal
Author: Adem Kurt
License: MIT
Requires-Python: >=3.7
License-File: LICENSE
Requires-Dist: pyperclip
Dynamic: license-file
